proxai/__init__.py
proxai/caching/__init__.py
proxai/caching/model_cache.py
proxai/caching/query_cache.py
proxai/connections/__init__.py
proxai/connections/available_models.py
proxai/connections/proxdash.py
proxai/connectors/__init__.py
proxai/connectors/model_configs.py
proxai/connectors/model_configs_data/__init__.py
proxai/connectors/model_configs_data/example_proxdash_model_configs.json
proxai/connectors/model_configs_data/v1.0.4.json
proxai/connectors/model_connector.py
proxai/connectors/model_registry.py
proxai/connectors/providers/claude.py
proxai/connectors/providers/claude_mock.py
proxai/connectors/providers/cohere_api.py
proxai/connectors/providers/cohere_api_mock.py
proxai/connectors/providers/databricks.py
proxai/connectors/providers/databricks_mock.py
proxai/connectors/providers/deepseek.py
proxai/connectors/providers/gemini.py
proxai/connectors/providers/gemini_mock.py
proxai/connectors/providers/grok.py
proxai/connectors/providers/huggingface.py
proxai/connectors/providers/huggingface_mock.py
proxai/connectors/providers/mistral.py
proxai/connectors/providers/mistral_mock.py
proxai/connectors/providers/mock_provider.py
proxai/connectors/providers/openai.py
proxai/connectors/providers/openai_mock.py
proxai/experiment/__init__.py
proxai/experiment/experiment.py
proxai/logging/__init__.py
proxai/logging/utils.py
proxai/proxai.py
proxai/serializers/hash_serializer.py
proxai/serializers/type_serializer.py
proxai/stat_types.py
proxai/state_controllers/state_controller.py
proxai/type_utils.py
proxai/types.py
proxai-0.2.12.dist-info/METADATA
proxai-0.2.12.dist-info/WHEEL
proxai-0.2.12.dist-info/licenses/LICENSE
proxai-0.2.12.dist-info/RECORD
