Metadata-Version: 2.4
Name: proxai
Version: 0.2.12
Summary: ProxAI is a lightweight abstraction layer for foundational AI model connections.
License: MIT
License-File: LICENSE
Author: proxai
Requires-Python: >=3.9,<4.0
Classifier: License :: OSI Approved :: MIT License
Classifier: Programming Language :: Python :: 3
Classifier: Programming Language :: Python :: 3.9
Classifier: Programming Language :: Python :: 3.10
Classifier: Programming Language :: Python :: 3.11
Classifier: Programming Language :: Python :: 3.12
Classifier: Programming Language :: Python :: 3.13
Classifier: Programming Language :: Python :: 3.14
Requires-Dist: anthropic (>=0.75.0,<0.76.0)
Requires-Dist: cohere (>=5.20.0,<6.0.0)
Requires-Dist: databricks-sdk[openai] (>=0.73.0,<0.74.0)
Requires-Dist: google-genai (<1.9.0)
Requires-Dist: mistralai (>=1.9.11,<2.0.0)
Requires-Dist: openai (>=1.14.3,<2.0.0)
Requires-Dist: packaging (>=24.0,<25.0)
Requires-Dist: platformdirs (>=4.0.0,<5.0.0)
Requires-Dist: urllib3 (<2.0.0)
Project-URL: Homepage, https://proxai.co
Project-URL: Issues, https://github.com/proxai/proxai/issues
Project-URL: Repository, https://github.com/proxai/proxai
